dv_flow/libformal/__ext__.py
dv_flow/libformal/__init__.py
dv_flow/libformal/flow.dv
dv_flow/libformal/flow_sby.dv
dv_flow/libformal/sby_bmc.py
dv_flow_libformal-0.0.119397187157rc0.dist-info/licenses/LICENSE
dv_flow_libformal-0.0.119397187157rc0.dist-info/METADATA
dv_flow_libformal-0.0.119397187157rc0.dist-info/WHEEL
dv_flow_libformal-0.0.119397187157rc0.dist-info/entry_points.txt
dv_flow_libformal-0.0.119397187157rc0.dist-info/top_level.txt
dv_flow_libformal-0.0.119397187157rc0.dist-info/RECORD
