Metadata-Version: 2.4
Name: dv-flow-libformal
Version: 0.0.119397187157rc0
Summary: Provides dv-flow tasks for formal verification (skeleton)
Author-email: Matthew Ballance <matt.ballance@gmail.com>
License:                                  Apache License
License-File: LICENSE
Requires-Dist: dv-flow-mgr
Requires-Dist: toposort
Dynamic: license-file
